Mr_Searcher.py
mr_searcher-1.4.2.3.dist-info/licenses/LICENSE
mr_searcher-1.4.2.3.dist-info/METADATA
mr_searcher-1.4.2.3.dist-info/WHEEL
mr_searcher-1.4.2.3.dist-info/entry_points.txt
mr_searcher-1.4.2.3.dist-info/top_level.txt
mr_searcher-1.4.2.3.dist-info/RECORD
