Metadata-Version: 2.4
Name: mr-searcher
Version: 1.4.2.3
Summary: A non-hostile, terminal-based information retrieval utility using DuckDuckGo.
Home-page: https://github.com/YourUsername/MrSearcher
Author: Om Shailesh Vetale
Author-email: omvetale.legend@gmail.com
License: MIT
Keywords: cli search utility duckduckgo terminal
Classifier: Development Status :: 4 - Beta
Classifier: Intended Audience :: End Users/Desktop
Classifier: Topic :: Internet :: WWW/HTTP :: Indexing/Search
Classifier: License :: OSI Approved :: MIT License
Classifier: Programming Language :: Python :: 3
Classifier: Programming Language :: Python :: 3.8
Classifier: Programming Language :: Python :: 3.9
Classifier: Programming Language :: Python :: 3.10
License-File: LICENSE
Requires-Dist: psutil
Requires-Dist: pyfiglet
Requires-Dist: colorama
Requires-Dist: duckduckgo-search
Requires-Dist: autocorrect
Requires-Dist: pyspellchecker
Requires-Dist: numpy
Requires-Dist: yt-dlp
Requires-Dist: qrcode
Provides-Extra: transcribe
Requires-Dist: openai-whisper; extra == "transcribe"
Requires-Dist: numpy; extra == "transcribe"
Provides-Extra: media
Requires-Dist: pygame; extra == "media"
Dynamic: author
Dynamic: author-email
Dynamic: classifier
Dynamic: description
Dynamic: description-content-type
Dynamic: home-page
Dynamic: keywords
Dynamic: license
Dynamic: license-file
Dynamic: provides-extra
Dynamic: requires-dist
Dynamic: summary
